venvrun.py
venv_run-0.2.0.dist-info/LICENSE
venv_run-0.2.0.dist-info/METADATA
venv_run-0.2.0.dist-info/WHEEL
venv_run-0.2.0.dist-info/entry_points.txt
venv_run-0.2.0.dist-info/top_level.txt
venv_run-0.2.0.dist-info/RECORD
