Metadata-Version: 2.1
Name: venv-run
Version: 0.2.0
Summary: Run commands using Python virtual environment
Home-page: https://github.com/guludo/venv-run
Author: Gustavo José de Sousa
Author-email: gustavo.jo.sousa@gmail.com
Project-URL: Changelog, https://github.com/guludo/venv-run/blob/master/CHANGELOG.md
Classifier: Development Status :: 3 - Alpha
Classifier: Environment :: Console
Classifier: Intended Audience :: Developers
Classifier: Intended Audience :: System Administrators
Classifier: License :: OSI Approved :: GNU Lesser General Public License v3 (LGPLv3)
Classifier: Topic :: Software Development
Classifier: Topic :: Utilities
Requires-Python: ~=3.5
License-File: LICENSE
